nested_type_checker/__init__.py
nested_type_checker/is_object_of_type_module.py
nested_type_checker-0.9.7.dist-info/METADATA
nested_type_checker-0.9.7.dist-info/WHEEL
nested_type_checker-0.9.7.dist-info/top_level.txt
nested_type_checker-0.9.7.dist-info/RECORD
