Metadata-Version: 2.1
Name: nested_type_checker
Version: 0.9.7
Summary: A runtime strict type-checking module for Python designed to validate parametrized (nested) types.
Home-page: https://github.com/JokeUrSelf/nested-type-checker
Author: JokeUrSelf
License: MIT
Platform: any
Classifier: Programming Language :: Python :: 3
Classifier: License :: OSI Approved :: MIT License
Classifier: Operating System :: OS Independent
Requires-Python: >=3.5
